groupdocs/viewer/py.typed
aspose/pycore/py.typed
aspose/pycore/__init__.pyi
aspose/pyreflection/py.typed
aspose/pyreflection/__init__.pyi
aspose/pydrawing/py.typed
aspose/pydrawing/__init__.pyi
aspose/pydrawing/design.pyi
aspose/pydrawing/drawing2d.pyi
aspose/pydrawing/imaging.pyi
aspose/pydrawing/printing.pyi
aspose/pydrawing/text.pyi
groupdocs/viewer/__init__.pyi
groupdocs/viewer/caching/__init__.pyi
groupdocs/viewer/drawing/__init__.pyi
groupdocs/viewer/exceptions/__init__.pyi
groupdocs/viewer/fonts/__init__.pyi
groupdocs/viewer/interfaces/__init__.pyi
groupdocs/viewer/logging/__init__.pyi
groupdocs/viewer/options/__init__.pyi
groupdocs/viewer/results/__init__.pyi
.__pyi_patched
groupdocs/__init__.py
groupdocs/pycore.cp310-win32.pyd
groupdocs/pycore.cp311-win32.pyd
groupdocs/pycore.cp312-win32.pyd
groupdocs/pycore.cp313-win32.pyd
groupdocs/pycore.cp35-win32.pyd
groupdocs/pycore.cp36-win32.pyd
groupdocs/pycore.cp37-win32.pyd
groupdocs/pycore.cp38-win32.pyd
groupdocs/pycore.cp39-win32.pyd
groupdocs/pygc.cp310-win32.pyd
groupdocs/pygc.cp311-win32.pyd
groupdocs/pygc.cp312-win32.pyd
groupdocs/pygc.cp313-win32.pyd
groupdocs/pygc.cp35-win32.pyd
groupdocs/pygc.cp36-win32.pyd
groupdocs/pygc.cp37-win32.pyd
groupdocs/pygc.cp38-win32.pyd
groupdocs/pygc.cp39-win32.pyd
groupdocs/pyreflection.cp310-win32.pyd
groupdocs/pyreflection.cp311-win32.pyd
groupdocs/pyreflection.cp312-win32.pyd
groupdocs/pyreflection.cp313-win32.pyd
groupdocs/pyreflection.cp35-win32.pyd
groupdocs/pyreflection.cp36-win32.pyd
groupdocs/pyreflection.cp37-win32.pyd
groupdocs/pyreflection.cp38-win32.pyd
groupdocs/pyreflection.cp39-win32.pyd
groupdocs/viewer.cp310-win32.pyd
groupdocs/viewer.cp311-win32.pyd
groupdocs/viewer.cp312-win32.pyd
groupdocs/viewer.cp313-win32.pyd
groupdocs/viewer.cp35-win32.pyd
groupdocs/viewer.cp36-win32.pyd
groupdocs/viewer.cp37-win32.pyd
groupdocs/viewer.cp38-win32.pyd
groupdocs/viewer.cp39-win32.pyd
groupdocs/__pyinstaller/__init__.pyi
groupdocs/__pyinstaller/hook-aspose.py
groupdocs_viewer_net-25.12.dist-info/METADATA
groupdocs_viewer_net-25.12.dist-info/WHEEL
groupdocs_viewer_net-25.12.dist-info/entry_points.txt
groupdocs_viewer_net-25.12.dist-info/top_level.txt
groupdocs_viewer_net-25.12.dist-info/RECORD
