Metadata-Version: 2.1
Name: groupdocs-viewer-net
Version: 25.12
Summary: GroupDocs.Viewer for Python via .NET is a document viewer API that supports over 180 file types and enables developers to easily render files to various formats, such as PDF, HTML, JPG, or PNG. With this API, you can seamlessly render a wide range of file types, including popular OpenDocument and Microsoft Office formats like DOCS, XLSX, and PPTX, as well as specialized CAD and graphic editor files like DWG, DXF, PSD, AI, and CDR. Supports Python 3.5 to 3.13 (Python <3.14).
Home-page: https://products.groupdocs.com/viewer/python-net/
Author: GroupDocs
License: Other/Proprietary License
Keywords: viewer,view,file,render,api,pdf,docx,xlsx,pptx,html,png,word,excel,powerpoint,visio,opendocument,photoshop
Platform: win32
Classifier: Operating System :: Microsoft :: Windows
Classifier: Operating System :: POSIX :: Linux
Classifier: Operating System :: Unix
Classifier: License :: Other/Proprietary License
Classifier: Programming Language :: Python
Classifier: Programming Language :: Python :: 3
Classifier: Programming Language :: Python :: 3 :: Only
Classifier: Programming Language :: Python :: 3.5
Classifier: Programming Language :: Python :: 3.6
Classifier: Programming Language :: Python :: 3.7
Classifier: Programming Language :: Python :: 3.8
Classifier: Programming Language :: Python :: 3.9
Classifier: Programming Language :: Python :: 3.10
Classifier: Programming Language :: Python :: 3.11
Classifier: Programming Language :: Python :: 3.12
Classifier: Programming Language :: Python :: 3.13
Classifier: Topic :: Multimedia :: Graphics :: Viewers
Classifier: Topic :: Software Development :: Libraries
Classifier: Topic :: Utilities
Requires-Python: >=3.5,<3.14
